README.md
setup.py
bi_tools/BILogger.py
bi_tools/BIParser.py
bi_tools/SnowflakeLogger.py
bi_tools/__init__.py
bi_tools/bi_exceptions.py
bi_tools/biz_intel_creds.py
bi_tools/eztests.py
bi_tools/eztools.py
bi_tools.egg-info/PKG-INFO
bi_tools.egg-info/SOURCES.txt
bi_tools.egg-info/dependency_links.txt
bi_tools.egg-info/top_level.txt