Metadata-Version: 1.1
Name: bi-tools
Version: 0.1.9
Summary: PitchBook Business Intelligence Python Toolbox
Home-page: https://git.pitchbookdata.com/business-intelligence/bi_tools
Author: BI Data Engineering
Author-email: jun.kim@pitchbook.com
License: UNKNOWN
Platform: UNKNOWN
Classifier: Programming Language :: Python :: 2
Classifier: Programming Language :: Python :: 3
Classifier: License :: OSI Approved :: MIT License
Classifier: Operating System :: OS Independent
